{"image rotation": 0, "value": [{"x": 0.634286, "y": 0.175238, "width": 9.14286, "height": 19.0476, "rotation": 0, "rectanglelabels": ["object"]}, {"x": 0.632857, "y": 0.393333, "width": 9.42857, "height": 18.0952, "rotation": 0, "rectanglelabels": ["object"]}, {"x": 0.632857, "y": 0.282857, "width": 9.42857, "height": 40.1905, "rotation": 0, "rectanglelabels": ["object"]}, {"x": 0.142857, "y": 0.439048, "width": 9.42857, "height": 12.7619, "rotation": 0, "rectanglelabels": ["object"]}, {"x": 0.106429, "y": 0.797143, "width": 19.2857, "height": 37.9048, "rotation": 0, "rectanglelabels": ["object"]}, {"x": 0.0435714, "y": 0.440952, "width": 8.71429, "height": 12.7619, "rotation": 0, "rectanglelabels": ["object"]}, {"x": 0.0364286, "y": 0.165714, "width": 7.285709999999999, "height": 14.0952, "rotation": 0, "rectanglelabels": ["object"]}, {"x": 0.0371429, "y": 0.305714, "width": 7.42857, "height": 13.1429, "rotation": 0, "rectanglelabels": ["object"]}, {"x": 0.777143, "y": 0.301905, "width": 18.5714, "height": 36.381, "rotation": 0, "rectanglelabels": ["object"]}, {"x": 0.904286, "y": 0.78, "width": 19.142899999999997, "height": 37.1429, "rotation": 0, "rectanglelabels": ["object"]}, {"x": 0.131429, "y": 0.301905, "width": 9.71429, "height": 13.5238, "rotation": 0, "rectanglelabels": ["object"]}, {"x": 0.937857, "y": 0.295238, "width": 12.4286, "height": 36.1905, "rotation": 0, "rectanglelabels": ["object"]}, {"x": 0.306429, "y": 0.791429, "width": 20.1429, "height": 37.9048, "rotation": 0, "rectanglelabels": ["object"]}, {"x": 0.23, "y": 0.195238, "width": 10.0, "height": 21.1429, "rotation": 0, "rectanglelabels": ["object"]}, {"x": 0.242143, "y": 0.400952, "width": 9.0, "height": 19.619, "rotation": 0, "rectanglelabels": ["object"]}, {"x": 0.705, "y": 0.779048, "width": 20.1429, "height": 40.761900000000004, "rotation": 0, "rectanglelabels": ["object"]}, {"x": 0.437143, "y": 0.395238, "width": 9.14286, "height": 18.8571, "rotation": 0, "rectanglelabels": ["object"]}, {"x": 0.339286, "y": 0.399048, "width": 9.28571, "height": 19.2381, "rotation": 0, "rectanglelabels": ["object"]}, {"x": 0.505, "y": 0.795238, "width": 19.2857, "height": 37.1429, "rotation": 0, "rectanglelabels": ["object"]}, {"x": 0.535, "y": 0.393333, "width": 9.28571, "height": 18.8571, "rotation": 0, "rectanglelabels": ["object"]}, {"x": 0.534286, "y": 0.186667, "width": 9.71429, "height": 20.952399999999997, "rotation": 0, "rectanglelabels": ["object"]}, {"x": 0.331429, "y": 0.193333, "width": 9.71429, "height": 21.1429, "rotation": 0, "rectanglelabels": ["object"]}, {"x": 0.432857, "y": 0.190476, "width": 9.71429, "height": 21.3333, "rotation": 0, "rectanglelabels": ["object"]}]}